uwcip/sharedutils/__init__.py
uwcip/sharedutils/configutils.py
uwcip/sharedutils/fileutils.py
uwcip/sharedutils/loggingutils.py
uwcip_sharedutils-0.1.0.dist-info/WHEEL
uwcip_sharedutils-0.1.0.dist-info/METADATA
uwcip_sharedutils-0.1.0.dist-info/RECORD
